Classfile /C:/Users/worker/IdeaProjects/SC/JavaDecompiler/cli/CommandLineConstants.class
  Last modified 1 џэт. 2010 у.; size 1517 bytes
  SHA-256 checksum 41c40d88e6ae09cb169f4c8c6116c5c5d6c23f3bce3008e61173632a9d08e8b8
  Compiled from "CommandLineConstants.scala"
public final class io.gatling.app.cli.CommandLineConstants
  minor version: 0
  major version: 52
  flags: (0x0031) ACC_PUBLIC, ACC_FINAL, ACC_SUPER
  this_class: #2                          // io/gatling/app/cli/CommandLineConstants
  super_class: #4                         // java/lang/Object
  interfaces: 0, fields: 0, methods: 8, attributes: 3
Constant pool:
   #1 = Utf8               io/gatling/app/cli/CommandLineConstants
   #2 = Class              #1             // io/gatling/app/cli/CommandLineConstants
   #3 = Utf8               java/lang/Object
   #4 = Class              #3             // java/lang/Object
   #5 = Utf8               CommandLineConstants.scala
   #6 = Utf8               Lscala/reflect/ScalaSignature;
   #7 = Utf8               bytes
   #8 = Utf8               \u0006\u0005\u0005;Qa\u0005\u000b\t\nu1Qa\b\u000b\t\n\u0001BQaJ\u0001\u0005\u0002!Bq!K\u0001C\u0002\u0013\u0005!\u0006\u0003\u00043\u0003\u0001\u0006Ia\u000b\u0005\bg\u0005\u0011\r\u0011\"\u0001+\u0011\u0019!\u0014\u0001)A\u0005W!9Q\'\u0001b\u0001\n\u0003Q\u0003B\u0002\u001c\u0002A\u0003%1\u0006C\u00048\u0003\t\u0007I\u0011\u0001\u0016\t\ra\n\u0001\u0015!\u0003,\u0011\u001dI\u0014A1A\u0005\u0002)BaAO\u0001!\u0002\u0013Y\u0003bB\u001e\u0002\u0005\u0004%\tA\u000b\u0005\u0007y\u0005\u0001\u000b\u0011B\u0016\t\u000fu\n!\u0019!C\u0001U!1a(\u0001Q\u0001\n-BqaP\u0001C\u0002\u0013\u0005!\u0006\u0003\u0004A\u0003\u0001\u0006IaK\u0001\u0015\u0007>lW.\u00198e\u0019&tWmQ8ogR\fg\u000e^:\u000b\u0005U1\u0012aA2mS*\u0011q\u0003G\u0001\u0004CB\u0004(BA\r\u001b\u0003\u001d9\u0017\r\u001e7j]\u001eT\u0011aG\u0001\u0003S>\u001c\u0001\u0001\u0005\u0002\u001f\u00035\tAC\u0001\u000bD_6l\u0017M\u001c3MS:,7i\u001c8ti\u0006tGo]\n\u0003\u0003\u0005\u0002\"AI\u0013\u000e\u0003\rR\u0011\u0001J\u0001\u0006g\u000e\fG.Y\u0005\u0003M\r\u0012a!\u00118z%\u00164\u0017A\u0002\u001fj]&$h\bF\u0001\u001e\u0003\u0011AU\r\u001c9\u0016\u0003-\u0002\"\u0001\f\u0019\u000e\u00035R!!\u0006\u0018\u000b\u0005=B\u0012\u0001B2pe\u0016L!!M\u0017\u0003\'\r{W.\\1oI2Kg.Z\"p]N$\u0018M\u001c;\u0002\u000b!+G\u000e\u001d\u0011\u0002\u00139{\'+\u001a9peR\u001c\u0018A\u0003(p%\u0016\u0004xN\u001d;tA\u0005Y!+\u001a9peR\u001cxJ\u001c7z\u00031\u0011V\r]8siN|e\u000e\\=!\u00035\u0011Vm];miN4u\u000e\u001c3fe\u0006q!+Z:vYR\u001chi\u001c7eKJ\u0004\u0013a\u0004*fg>,(oY3t\r>dG-\u001a:\u0002!I+7o\\;sG\u0016\u001chi\u001c7eKJ\u0004\u0013A\u0004\"j]\u0006\u0014\u0018.Z:G_2$WM]\u0001\u0010\u0005&t\u0017M]5fg\u001a{G\u000eZ3sA\u0005Q1+[7vY\u0006$\u0018n\u001c8\u0002\u0017MKW.\u001e7bi&|g\u000eI\u0001\u000f%VtG)Z:de&\u0004H/[8o\u0003=\u0011VO\u001c#fg\u000e\u0014\u0018\u000e\u001d;j_:\u0004\u0003
   #9 = Utf8               RunDescription
  #10 = Utf8               ()Lio/gatling/core/cli/CommandLineConstant;
  #11 = Utf8               io/gatling/app/cli/CommandLineConstants$
  #12 = Class              #11            // io/gatling/app/cli/CommandLineConstants$
  #13 = Utf8               MODULE$
  #14 = Utf8               Lio/gatling/app/cli/CommandLineConstants$;
  #15 = NameAndType        #13:#14        // MODULE$:Lio/gatling/app/cli/CommandLineConstants$;
  #16 = Fieldref           #12.#15        // io/gatling/app/cli/CommandLineConstants$.MODULE$:Lio/gatling/app/cli/CommandLineConstants$;
  #17 = NameAndType        #9:#10         // RunDescription:()Lio/gatling/core/cli/CommandLineConstant;
  #18 = Methodref          #12.#17        // io/gatling/app/cli/CommandLineConstants$.RunDescription:()Lio/gatling/core/cli/CommandLineConstant;
  #19 = Utf8               Simulation
  #20 = NameAndType        #19:#10        // Simulation:()Lio/gatling/core/cli/CommandLineConstant;
  #21 = Methodref          #12.#20        // io/gatling/app/cli/CommandLineConstants$.Simulation:()Lio/gatling/core/cli/CommandLineConstant;
  #22 = Utf8               BinariesFolder
  #23 = NameAndType        #22:#10        // BinariesFolder:()Lio/gatling/core/cli/CommandLineConstant;
  #24 = Methodref          #12.#23        // io/gatling/app/cli/CommandLineConstants$.BinariesFolder:()Lio/gatling/core/cli/CommandLineConstant;
  #25 = Utf8               ResourcesFolder
  #26 = NameAndType        #25:#10        // ResourcesFolder:()Lio/gatling/core/cli/CommandLineConstant;
  #27 = Methodref          #12.#26        // io/gatling/app/cli/CommandLineConstants$.ResourcesFolder:()Lio/gatling/core/cli/CommandLineConstant;
  #28 = Utf8               ResultsFolder
  #29 = NameAndType        #28:#10        // ResultsFolder:()Lio/gatling/core/cli/CommandLineConstant;
  #30 = Methodref          #12.#29        // io/gatling/app/cli/CommandLineConstants$.ResultsFolder:()Lio/gatling/core/cli/CommandLineConstant;
  #31 = Utf8               ReportsOnly
  #32 = NameAndType        #31:#10        // ReportsOnly:()Lio/gatling/core/cli/CommandLineConstant;
  #33 = Methodref          #12.#32        // io/gatling/app/cli/CommandLineConstants$.ReportsOnly:()Lio/gatling/core/cli/CommandLineConstant;
  #34 = Utf8               NoReports
  #35 = NameAndType        #34:#10        // NoReports:()Lio/gatling/core/cli/CommandLineConstant;
  #36 = Methodref          #12.#35        // io/gatling/app/cli/CommandLineConstants$.NoReports:()Lio/gatling/core/cli/CommandLineConstant;
  #37 = Utf8               Help
  #38 = NameAndType        #37:#10        // Help:()Lio/gatling/core/cli/CommandLineConstant;
  #39 = Methodref          #12.#38        // io/gatling/app/cli/CommandLineConstants$.Help:()Lio/gatling/core/cli/CommandLineConstant;
  #40 = Utf8               Code
  #41 = Utf8               SourceFile
  #42 = Utf8               RuntimeVisibleAnnotations
  #43 = Utf8               ScalaSig
{
  public static io.gatling.core.cli.CommandLineConstant RunDescription();
    descriptor: ()Lio/gatling/core/cli/CommandLineConstant;
    flags: (0x0009) ACC_PUBLIC, ACC_STATIC
    Code:
      stack=1, locals=0, args_size=0
         0: getstatic     #16                 // Field io/gatling/app/cli/CommandLineConstants$.MODULE$:Lio/gatling/app/cli/CommandLineConstants$;
         3: invokevirtual #18                 // Method io/gatling/app/cli/CommandLineConstants$.RunDescription:()Lio/gatling/core/cli/CommandLineConstant;
         6: areturn

  public static io.gatling.core.cli.CommandLineConstant Simulation();
    descriptor: ()Lio/gatling/core/cli/CommandLineConstant;
    flags: (0x0009) ACC_PUBLIC, ACC_STATIC
    Code:
      stack=1, locals=0, args_size=0
         0: getstatic     #16                 // Field io/gatling/app/cli/CommandLineConstants$.MODULE$:Lio/gatling/app/cli/CommandLineConstants$;
         3: invokevirtual #21                 // Method io/gatling/app/cli/CommandLineConstants$.Simulation:()Lio/gatling/core/cli/CommandLineConstant;
         6: areturn

  public static io.gatling.core.cli.CommandLineConstant BinariesFolder();
    descriptor: ()Lio/gatling/core/cli/CommandLineConstant;
    flags: (0x0009) ACC_PUBLIC, ACC_STATIC
    Code:
      stack=1, locals=0, args_size=0
         0: getstatic     #16                 // Field io/gatling/app/cli/CommandLineConstants$.MODULE$:Lio/gatling/app/cli/CommandLineConstants$;
         3: invokevirtual #24                 // Method io/gatling/app/cli/CommandLineConstants$.BinariesFolder:()Lio/gatling/core/cli/CommandLineConstant;
         6: areturn

  public static io.gatling.core.cli.CommandLineConstant ResourcesFolder();
    descriptor: ()Lio/gatling/core/cli/CommandLineConstant;
    flags: (0x0009) ACC_PUBLIC, ACC_STATIC
    Code:
      stack=1, locals=0, args_size=0
         0: getstatic     #16                 // Field io/gatling/app/cli/CommandLineConstants$.MODULE$:Lio/gatling/app/cli/CommandLineConstants$;
         3: invokevirtual #27                 // Method io/gatling/app/cli/CommandLineConstants$.ResourcesFolder:()Lio/gatling/core/cli/CommandLineConstant;
         6: areturn

  public static io.gatling.core.cli.CommandLineConstant ResultsFolder();
    descriptor: ()Lio/gatling/core/cli/CommandLineConstant;
    flags: (0x0009) ACC_PUBLIC, ACC_STATIC
    Code:
      stack=1, locals=0, args_size=0
         0: getstatic     #16                 // Field io/gatling/app/cli/CommandLineConstants$.MODULE$:Lio/gatling/app/cli/CommandLineConstants$;
         3: invokevirtual #30                 // Method io/gatling/app/cli/CommandLineConstants$.ResultsFolder:()Lio/gatling/core/cli/CommandLineConstant;
         6: areturn

  public static io.gatling.core.cli.CommandLineConstant ReportsOnly();
    descriptor: ()Lio/gatling/core/cli/CommandLineConstant;
    flags: (0x0009) ACC_PUBLIC, ACC_STATIC
    Code:
      stack=1, locals=0, args_size=0
         0: getstatic     #16                 // Field io/gatling/app/cli/CommandLineConstants$.MODULE$:Lio/gatling/app/cli/CommandLineConstants$;
         3: invokevirtual #33                 // Method io/gatling/app/cli/CommandLineConstants$.ReportsOnly:()Lio/gatling/core/cli/CommandLineConstant;
         6: areturn

  public static io.gatling.core.cli.CommandLineConstant NoReports();
    descriptor: ()Lio/gatling/core/cli/CommandLineConstant;
    flags: (0x0009) ACC_PUBLIC, ACC_STATIC
    Code:
      stack=1, locals=0, args_size=0
         0: getstatic     #16                 // Field io/gatling/app/cli/CommandLineConstants$.MODULE$:Lio/gatling/app/cli/CommandLineConstants$;
         3: invokevirtual #36                 // Method io/gatling/app/cli/CommandLineConstants$.NoReports:()Lio/gatling/core/cli/CommandLineConstant;
         6: areturn

  public static io.gatling.core.cli.CommandLineConstant Help();
    descriptor: ()Lio/gatling/core/cli/CommandLineConstant;
    flags: (0x0009) ACC_PUBLIC, ACC_STATIC
    Code:
      stack=1, locals=0, args_size=0
         0: getstatic     #16                 // Field io/gatling/app/cli/CommandLineConstants$.MODULE$:Lio/gatling/app/cli/CommandLineConstants$;
         3: invokevirtual #39                 // Method io/gatling/app/cli/CommandLineConstants$.Help:()Lio/gatling/core/cli/CommandLineConstant;
         6: areturn
}
SourceFile: "CommandLineConstants.scala"
RuntimeVisibleAnnotations:
  0: #6(#7=s#8)
    scala.reflect.ScalaSignature(
      bytes="\u0006\u0005\u0005;Qa\u0005\u000b\t\nu1Qa\b\u000b\t\n\u0001BQaJ\u0001\u0005\u0002!Bq!K\u0001C\u0002\u0013\u0005!\u0006\u0003\u00043\u0003\u0001\u0006Ia\u000b\u0005\bg\u0005\u0011\r\u0011\"\u0001+\u0011\u0019!\u0014\u0001)A\u0005W!9Q\'\u0001b\u0001\n\u0003Q\u0003B\u0002\u001c\u0002A\u0003%1\u0006C\u00048\u0003\t\u0007I\u0011\u0001\u0016\t\ra\n\u0001\u0015!\u0003,\u0011\u001dI\u0014A1A\u0005\u0002)BaAO\u0001!\u0002\u0013Y\u0003bB\u001e\u0002\u0005\u0004%\tA\u000b\u0005\u0007y\u0005\u0001\u000b\u0011B\u0016\t\u000fu\n!\u0019!C\u0001U!1a(\u0001Q\u0001\n-BqaP\u0001C\u0002\u0013\u0005!\u0006\u0003\u0004A\u0003\u0001\u0006IaK\u0001\u0015\u0007>lW.\u00198e\u0019&tWmQ8ogR\fg\u000e^:\u000b\u0005U1\u0012aA2mS*\u0011q\u0003G\u0001\u0004CB\u0004(BA\r\u001b\u0003\u001d9\u0017\r\u001e7j]\u001eT\u0011aG\u0001\u0003S>\u001c\u0001\u0001\u0005\u0002\u001f\u00035\tAC\u0001\u000bD_6l\u0017M\u001c3MS:,7i\u001c8ti\u0006tGo]\n\u0003\u0003\u0005\u0002\"AI\u0013\u000e\u0003\rR\u0011\u0001J\u0001\u0006g\u000e\fG.Y\u0005\u0003M\r\u0012a!\u00118z%\u00164\u0017A\u0002\u001fj]&$h\bF\u0001\u001e\u0003\u0011AU\r\u001c9\u0016\u0003-\u0002\"\u0001\f\u0019\u000e\u00035R!!\u0006\u0018\u000b\u0005=B\u0012\u0001B2pe\u0016L!!M\u0017\u0003\'\r{W.\\1oI2Kg.Z\"p]N$\u0018M\u001c;\u0002\u000b!+G\u000e\u001d\u0011\u0002\u00139{\'+\u001a9peR\u001c\u0018A\u0003(p%\u0016\u0004xN\u001d;tA\u0005Y!+\u001a9peR\u001cxJ\u001c7z\u00031\u0011V\r]8siN|e\u000e\\=!\u00035\u0011Vm];miN4u\u000e\u001c3fe\u0006q!+Z:vYR\u001chi\u001c7eKJ\u0004\u0013a\u0004*fg>,(oY3t\r>dG-\u001a:\u0002!I+7o\\;sG\u0016\u001chi\u001c7eKJ\u0004\u0013A\u0004\"j]\u0006\u0014\u0018.Z:G_2$WM]\u0001\u0010\u0005&t\u0017M]5fg\u001a{G\u000eZ3sA\u0005Q1+[7vY\u0006$\u0018n\u001c8\u0002\u0017MKW.\u001e7bi&|g\u000eI\u0001\u000f%VtG)Z:de&\u0004H/[8o\u0003=\u0011VO\u001c#fg\u000e\u0014\u0018\u000e\u001d;j_:\u0004\u0003"
    )
  ScalaSig: length = 0x3 (unknown attribute)
   05 02 00
